multiprocessor/__init__.py
multiprocessor/multipro.py
multipro-0.0.1.dist-info/LICENSE
multipro-0.0.1.dist-info/METADATA
multipro-0.0.1.dist-info/WHEEL
multipro-0.0.1.dist-info/top_level.txt
multipro-0.0.1.dist-info/RECORD
